[
  {
    "reveal_id": "2afcd31fa3f44a18a3c0d720f550251b",
    "article_title": "Nepal Denies Border Restrictions for Indians",
    "question": "What did Nepal recently deny regarding Indian tourists?",
    "answer_label": "A",
    "answer_text": "Imposing strict border checks",
    "explanation": "Nepal denied reports of strict border checks and mandatory IDs for Indian tourists.",
    "due_at": "2026-05-14T00:43:14.080269+00:00"
  },
  {
    "reveal_id": "7a1048ef48014e02972495adf3837d04",
    "article_title": "Nepal Denies Border Restrictions for Indians",
    "question": "What is the purpose of Nepal's new digital system?",
    "answer_label": "B",
    "answer_text": "To simplify vehicle entry procedures",
    "explanation": "The new digital system aims to simplify vehicle entry procedures for tourists.",
    "due_at": "2026-05-14T00:43:14.913526+00:00"
  },
  {
    "reveal_id": "c9c1f9c7e15045cb901e2a484015a886",
    "article_title": "Nepal Denies Border Restrictions for Indians",
    "question": "How did Nepal describe reports of border restrictions for Indian tourists?",
    "answer_label": "B",
    "answer_text": "False, baseless, and misleading",
    "explanation": "Nepal described the reports as false, baseless, and misleading.",
    "due_at": "2026-05-14T00:43:15.616389+00:00"
  },
  {
    "reveal_id": "257ad5e8ab64431eb5eed4b01b3ba8c6",
    "article_title": "SpaceX Plans Advanced Spaceports",
    "question": "What is SpaceX planning to build to support future space travel?",
    "answer_label": "B",
    "answer_text": "Advanced spaceports",
    "explanation": "SpaceX is planning to build advanced spaceports to support future Mars and lunar travel.",
    "due_at": "2026-05-14T00:43:22.864992+00:00"
  },
  {
    "reveal_id": "4417359041ff4f5da0312d0e7259c828",
    "article_title": "SpaceX Plans Advanced Spaceports",
    "question": "What can advanced spaceports facilitate according to the article?",
    "answer_label": "C",
    "answer_text": "Frequent space travel",
    "explanation": "Advanced spaceports can facilitate frequent space travel, making it more accessible and efficient.",
    "due_at": "2026-05-14T00:43:23.570695+00:00"
  },
  {
    "reveal_id": "e8d5acab675b4e0284368d330d0cbed4",
    "article_title": "SpaceX Plans Advanced Spaceports",
    "question": "Why can India benefit from SpaceX's advanced spaceport project?",
    "answer_label": "C",
    "answer_text": "It can enhance India's space program",
    "explanation": "India can benefit from such developments, as it can enhance the country's space program and collaboration with international space agencies.",
    "due_at": "2026-05-14T00:43:30.603760+00:00"
  }
]