[
  {
    "reveal_id": "babeb7f3efce4ffbb600e8818c815bcd",
    "article_title": "Subnautica 2 Adaptations",
    "question": "What are Adaptations in Subnautica 2?",
    "answer_label": "B",
    "answer_text": "Biological upgrades",
    "explanation": "Adaptations are biological upgrades that help players survive in the alien ocean.",
    "due_at": "2026-05-17T20:27:24.293745+00:00"
  },
  {
    "reveal_id": "8b346774bb2345e0802af8fe5cb6e8ee",
    "article_title": "Subnautica 2 Adaptations",
    "question": "How do players acquire Adaptations in Subnautica 2?",
    "answer_label": "B",
    "answer_text": "By interacting with Angel Combs",
    "explanation": "Players acquire Adaptations by interacting with Angel Combs in the game.",
    "due_at": "2026-05-17T20:27:28.109269+00:00"
  },
  {
    "reveal_id": "fc2d90cdbb3e4f74a411a0483ee448be",
    "article_title": "Subnautica 2 Adaptations",
    "question": "What is the benefit of the Pressure Tolerance Adaptation?",
    "answer_label": "C",
    "answer_text": "Breathing pressurized air",
    "explanation": "The Pressure Tolerance Adaptation allows players to breathe pressurized air.",
    "due_at": "2026-05-17T20:27:28.749284+00:00"
  },
  {
    "reveal_id": "b75492c6082d4e91a986f9823163a310",
    "article_title": "Kerala Cabinet Formation",
    "question": "Who is the Chief Minister-designate of Kerala?",
    "answer_label": "A",
    "answer_text": "VD Satheesan",
    "explanation": "VD Satheesan is the Chief Minister-designate of Kerala, as mentioned in the article.",
    "due_at": "2026-05-17T20:27:35.790330+00:00"
  },
  {
    "reveal_id": "fdf51a8e320d4f2fbd7d03609839913c",
    "article_title": "Kerala Cabinet Formation",
    "question": "Which party is expected to form the government in Kerala?",
    "answer_label": "B",
    "answer_text": "UDF",
    "explanation": "The UDF government is expected to form the government in Kerala, as mentioned in the article.",
    "due_at": "2026-05-17T20:27:36.431196+00:00"
  },
  {
    "reveal_id": "4d5b60087bb44156a2eafdda711b5323",
    "article_title": "Kerala Cabinet Formation",
    "question": "When is the swearing-in ceremony of the new Kerala government expected to take place?",
    "answer_label": "B",
    "answer_text": "Monday",
    "explanation": "The swearing-in ceremony is expected to take place on Monday, as mentioned in the article.",
    "due_at": "2026-05-17T20:27:37.061732+00:00"
  }
]