[
  {
    "reveal_id": "1da26f9721394b0d850e896c8ce874c5",
    "article_title": "Delhi CM Visits LNJP Hospital",
    "question": "What was the occasion of the Delhi Chief Minister's visit to LNJP Hospital?",
    "answer_label": "B",
    "answer_text": "International Nurses Day",
    "explanation": "The visit was made on the eve of International Nurses Day to appreciate the nursing staff.",
    "due_at": "2026-05-13T11:34:36.139888+00:00"
  },
  {
    "reveal_id": "92b992ccbd9742d4ac23eda9830c363b",
    "article_title": "Delhi CM Visits LNJP Hospital",
    "question": "What was the previous stipend for nursing interns at LNJP Hospital?",
    "answer_label": "B",
    "answer_text": "Rs 500",
    "explanation": "The previous stipend was Rs 500, which has been increased to Rs 13,150.",
    "due_at": "2026-05-13T11:34:39.921159+00:00"
  },
  {
    "reveal_id": "c57aea9f51cf40db92c5cecdebceeb68",
    "article_title": "Delhi CM Visits LNJP Hospital",
    "question": "How many years did the nursing interns wait for the stipend increase?",
    "answer_label": "C",
    "answer_text": "27 years",
    "explanation": "The nursing interns had to wait for 27 years for the stipend increase.",
    "due_at": "2026-05-13T11:34:40.544608+00:00"
  },
  {
    "reveal_id": "3615aa9a56e54ce8926f624c70d2aea7",
    "article_title": "Union Minister Orders Probe on Bandhwari Landfill",
    "question": "What did Union Minister Rao Inderjit Singh order regarding the Bandhwari landfill?",
    "answer_label": "B",
    "answer_text": "A scientific study on its impact",
    "explanation": "The minister ordered a scientific study to assess the impact of the landfill on groundwater and public health.",
    "due_at": "2026-05-13T11:34:47.645699+00:00"
  },
  {
    "reveal_id": "fde1bae8b5b6495788467a9cb0f57ca5",
    "article_title": "Union Minister Orders Probe on Bandhwari Landfill",
    "question": "What is the purpose of the flood-control work in Gurugram?",
    "answer_label": "C",
    "answer_text": "To protect from waterlogging",
    "explanation": "The flood-control work aims to protect Gurugram from waterlogging and its associated problems.",
    "due_at": "2026-05-13T11:34:48.273679+00:00"
  },
  {
    "reveal_id": "bbbdb4e90c1b4cbe8120edf147daef62",
    "article_title": "Union Minister Orders Probe on Bandhwari Landfill",
    "question": "What committee meeting was chaired by Union Minister Rao Inderjit Singh?",
    "answer_label": "C",
    "answer_text": "District Development Coordination and Monitoring Committee",
    "explanation": "The minister chaired the District Development Coordination and Monitoring Committee (DISHA) meeting.",
    "due_at": "2026-05-13T11:34:48.957887+00:00"
  }
]